MANIFEST.in
setup.py
timebook_web/__init__.py
timebook_web.egg-info/PKG-INFO
timebook_web.egg-info/SOURCES.txt
timebook_web.egg-info/dependency_links.txt
timebook_web.egg-info/requires.txt
timebook_web.egg-info/top_level.txt
timebook_web/templates/500.html
timebook_web/templates/base.html
timebook_web/templates/dailygraph.html
timebook_web/templates/snapshot.html