Metadata-Version: 1.0
Name: timebook-web
Version: 3.5.1
Summary: Be transparent.
Home-page: http://bitbucket.org/latestrevision/timebook_web/
Author: Adam Coddington
Author-email: me@adamcoddington.net
License: UNKNOWN
Platform: UNKNOWN
Classifier: Intended Audience :: Developers
Classifier: License :: OSI Approved :: MIT License
Classifier: Operating System :: OS Independent
Classifier: Programming Language :: Python
Classifier: Topic :: Utilities
